{"object":{"id":"iauth_1P94bBP2lzb2oXI9ak5RtqRH","object":"issuing.authorization","amount":100,"amount_details":{"atm_fee":null,"cashback_amount":0},"approved":false,"authorization_method":"online","balance_transactions":[],"card":{"id":"ic_1P8tcNP2lzb2oXI9TPSA5uBz","object":"issuing.card","brand":"Visa","cancellation_reason":null,"cardholder":{"id":"ich_1P8tXIP2lzb2oXI9Ts9I3KQJ","object":"issuing.cardholder","billing":{"address":{"city":"San Francisco","country":"US","line1":"1234 Main Street","line2":null,"postal_code":"94111","state":"CA"}},"company":null,"created":1713917888,"email":"jenny.rosen@example.com","individual":{"card_issuing":{"user_terms_acceptance":{"date":1713918879,"ip":"187.3.2.180","user_agent":"Mozilla/5.0 (Windows NT 10.0; Win64; x64; rv:125.0) Gecko/20100101 Firefox/125.0"}},"dob":{"day":11,"month":11,"year":1999},"first_name":"Jenny","last_name":"Rosen","verification":{"document":{"back":null,"front":null}}},"livemode":false,"metadata":{},"name":"Jenny Rosen","phone_number":"+18888675309","preferred_locales":[],"requirements":{"disabled_reason":null,"past_due":[]},"spending_controls":{"allowed_categories":[],"allowed_merchant_countries":[],"blocked_categories":[],"blocked_merchant_countries":[],"spending_limits":[],"spending_limits_currency":null},"status":"active","type":"individual"},"created":1713918203,"currency":"usd","exp_month":3,"exp_year":2027,"last4":"0005","livemode":false,"metadata":{},"migrate_tokens_from":null,"personalization_design":null,"pin":null,"replaced_by":null,"replacement_for":null,"replacement_reason":null,"second_line":null,"shipping":null,"spending_controls":{"allowed_categories":null,"allowed_merchant_countries":null,"blocked_categories":null,"blocked_merchant_countries":null,"spending_limits":[{"amount":50000,"categories":[],"interval":"daily"}],"spending_limits_currency":"usd"},"status":"active","type":"virtual","wallets":{"apple_pay":{"eligible":true,"ineligible_reason":null},"google_pay":{"eligible":true,"ineligible_reason":null},"primary_account_identifier":null}},"cardholder":"ich_1P8tXIP2lzb2oXI9Ts9I3KQJ","created":1713960413,"currency":"usd","livemode":false,"merchant_amount":100,"merchant_currency":"usd","merchant_data":{"category":"transportation_services","category_code":"4789","city":"San Francisco","country":"US","name":"Rocket Rides","network_id":"1234567890","postal_code":"94103","state":"CA","terminal_id":"99999999","url":null},"metadata":{},"network_data":{"acquiring_institution_id":"123456","system_trace_audit_number":"1234567890","transaction_id":"test_146432929743641"},"pending_request":null,"request_history":[{"amount":100,"amount_details":{"atm_fee":null,"cashback_amount":null},"approved":false,"authorization_code":null,"created":1713960414,"currency":"usd","merchant_amount":100,"merchant_currency":"usd","network_risk_score":10,"reason":"webhook_timeout","reason_message":null,"requested_at":1705104000}],"status":"closed","token":null,"transactions":[],"verification_data":{"address_line1_check":"match","address_postal_code_check":"match","authentication_exemption":null,"cvc_check":"match","expiry_check":"match","postal_code":"94103","three_d_secure":null},"wallet":null}}